adafruit_hcsr04.py
adafruit_circuitpython_hcsr04-0.4.23.dist-info/licenses/LICENSE
adafruit_circuitpython_hcsr04-0.4.23.dist-info/METADATA
adafruit_circuitpython_hcsr04-0.4.23.dist-info/WHEEL
adafruit_circuitpython_hcsr04-0.4.23.dist-info/top_level.txt
adafruit_circuitpython_hcsr04-0.4.23.dist-info/RECORD
