Metadata-Version: 2.4
Name: adafruit-circuitpython-hcsr04
Version: 0.4.23
Summary: CircuitPython library for controlling HC-SR04 ultrasonic range sensors.
Author-email: Adafruit Industries <circuitpython@adafruit.com>
License: MIT
Project-URL: Homepage, https://github.com/adafruit/Adafruit_CircuitPython_HCSR04
Keywords: adafruit,hcsr04,hardware,micropython,circuitpython,ultrasonic
Classifier: Intended Audience :: Developers
Classifier: Topic :: Software Development :: Libraries
Classifier: Topic :: Software Development :: Embedded Systems
Classifier: Topic :: System :: Hardware
Classifier: License :: OSI Approved :: MIT License
Classifier: Programming Language :: Python :: 3
License-File: LICENSE
Requires-Dist: Adafruit-Blinka
Provides-Extra: optional
Dynamic: license-file
